FilesOp/File.py
FilesOp/__init__.py
FilesOp-1.2.6.dist-info/LICENSE
FilesOp-1.2.6.dist-info/METADATA
FilesOp-1.2.6.dist-info/WHEEL
FilesOp-1.2.6.dist-info/top_level.txt
FilesOp-1.2.6.dist-info/RECORD
