Metadata-Version: 2.1
Name: FilesOp
Version: 1.2.6
Summary: Gestionale dei file per usi interni
Home-page: https://github.com/KingKaitoKid/FileOperations
Author: King Kaito Kid
Author-email: djstrix@me.com
License: UNKNOWN
Platform: UNKNOWN
Classifier: Programming Language :: Python :: 3
Classifier: License :: OSI Approved :: MIT License
Classifier: Operating System :: OS Independent
Requires-Python: >=3.9.6
License-File: LICENSE
